tutturu.py
tutturu-0.4.2.dist-info/entry_points.txt
tutturu-0.4.2.dist-info/WHEEL
tutturu-0.4.2.dist-info/METADATA
tutturu-0.4.2.dist-info/RECORD
