Metadata-Version: 2.1
Name: tutturu
Version: 0.4.2
Summary: Simple test. Tut-turu))
Author: Denis Aseev
Author-email: brerfox33@gmail.com
Classifier: License :: OSI Approved :: MIT License
